LICENSE
thepeer_sdk/__init__.py
thepeer_sdk/core/__init__.py
thepeer_sdk/core/direct_charge.py
thepeer_sdk/core/links.py
thepeer_sdk/core/sdk_client.py
thepeer_sdk/core/send.py
thepeer_sdk/core/users.py
thepeer_sdk/exceptions.py
thepeer_sdk/utils/__init__.py
thepeer_sdk/utils/apiclient.py
thepeer_sdk-0.0.2.dist-info/LICENSE
thepeer_sdk-0.0.2.dist-info/WHEEL
thepeer_sdk-0.0.2.dist-info/METADATA
thepeer_sdk-0.0.2.dist-info/RECORD
