Metadata-Version: 2.1
Name: thepeer-sdk
Version: 0.0.2
Summary: Python SDK for Thepeer
Home-page: https://github.com/Emmarex/thepeer-sdk-python
License: Apache-2.0
Keywords: thepeer,thepeer-sdk
Author: Oluwafemi Tairu
Author-email: tairuoluwafemi09@gmail.com
Requires-Python: >=3.7.12,<4.0.0
Classifier: Development Status :: 4 - Beta
Classifier: Intended Audience :: Developers
Classifier: License :: OSI Approved :: Apache Software License
Classifier: Natural Language :: English
Classifier: Programming Language :: Python :: 3
Classifier: Programming Language :: Python :: 3.10
Classifier: Programming Language :: Python :: 3.11
Classifier: Programming Language :: Python :: 3.6
Classifier: Programming Language :: Python :: 3.7
Classifier: Programming Language :: Python :: 3.8
Classifier: Programming Language :: Python :: 3.9
Requires-Dist: requests (>=2.26.0,<3.0.0)
Project-URL: Repository, https://github.com/Emmarex/thepeer-sdk-python
